{
  "medical||emergency||Please call 999.": 7,
  "medical||emergency||Please call emergency services.": 5,
  "medical||emergency||I am not feeling well.": 5,
  "medical||emergency||I need a doctor.": 3,
  "medical||emergency||I need help.": 5,
  "medical||emergency||I am lost\u2014can you help me?": 6,
  "medical||generic||Please repeat.": 1,
  "medical||generic||One moment.": 1,
  "medical||clarify||Sorry, can you rephrase?": 1,
  "medical||clarify||Could you type that again?": 2,
  "medical||clarify||Please speak slowly.": 2,
  "medical||clarify||Can you show me on your phone?": 1,
  "medical||clarify||Do you mean this?": 2,
  "medical||clarify||I understand a little\u2014please repeat.": 2,
  "restaurant||generic||Could you type that?": 1,
  "restaurant||custom||hello": 5,
  "restaurant||custom||my name": 1,
  "restaurant||custom||Hello": 1,
  "restaurant||custom||my name is": 1,
  "restaurant||custom||Hello, may I have a burrito bowl please": 1,
  "restaurant||generic||Yes, a burrito bowl would be great.": 1,
  "restaurant||generic||Could you repeat that, please?": 1,
  "restaurant||generic||Thank you, I'll have the burrito bowl.": 1,
  "restaurant||clarify||I'd like to add a side of rice.": 1,
  "restaurant||clarify||Would it be possible to substitute the rice?": 1,
  "restaurant||clarify||That's perfect, thank you.": 2,
  "restaurant||clarify||And can I get a side of beans as well?": 1,
  "medical||custom||Hello, I am here for the doctor's appointment": 3,
  "medical||custom||I might have a cough": 1,
  "medical||custom||I am here for the doctor's appointment": 1,
  "medical||emergency||Please let me know if I need to do anything.": 1,
  "medical||emergency||I'm happy to answer any questions.": 1,
  "medical||emergency||I'm feeling a bit nervous.": 1,
  "medical||emergency||I'll do my best to answer any questions.": 1,
  "medical||emergency||I'm here if you have any other requests.": 1,
  "medical||custom||I have a big lump on my throat is that bad": 1,
  "medical||emergency||Could you please check the lump on my throat?": 1,
  "medical||emergency||Please let me know if the lump requires any further testing.": 1,
  "medical||custom||Good morning": 1,
  "medical||custom||Hey I have a lump on my throat": 1,
  "medical||generic||This lump has been bothering me. Can we discuss it?": 1,
  "medical||custom||I have a lump on my throat": 2,
  "medical||generic||I need to get this checked out.": 1,
  "medical||generic||Do you have any recommendations for next steps?": 1,
  "medical||generic||Can you examine the lump for me?": 1,
  "medical||generic||I'd like to schedule an appointment with my doctor.": 1,
  "medical||generic||I'm concerned about this lump. What should I do next?": 1,
  "shopping||custom||I would like to buy fruit": 1,
  "shopping||generic||Could you please show me the options?": 1,
  "shopping||generic||I'm looking for fresh, high-quality fruit.": 1,
  "shopping||generic||I'm interested in seasonal, ripe produce.": 1,
  "shopping||custom||Do you have bananas": 1,
  "shopping||generic||Could you tell me about the different varieties?": 1,
  "shopping||generic||Could you describe the flavors of the different fruits?": 1,
  "medical||generic||Could you please examine the lump?": 1,
  "medical||generic||Do you have any idea what it might be?": 1,
  "medical||generic||I want to make sure this gets looked at.": 1,
  "shopping||custom||I would like to buy some fruit": 1,
  "shopping||generic||I'm interested in the organic produce section. Can you assist?": 1,
  "shopping||generic||Yes, I'd be happy to help you find some organic fruit.": 1,
  "medical||custom||Theres a lump on my throat": 1,
  "medical||generic||I'm concerned about this lump.": 1,
  "medical||generic||When can I see the doctor?": 1,
  "medical||generic||I'd like to get this checked out.": 1,
  "medical||emergency||Can you please schedule an appointment?": 1,
  "medical||emergency||Do I need a referral for this?": 1,
  "shopping||custom||I'd like to buy bananas": 1,
  "shopping||generic||Do you have any ripe ones?": 1,
  "shopping||generic||How much do the bananas cost?": 1,
  "shopping||generic||Where can I find the organic section?": 1,
  "shopping||directions||How are the bananas sourced and grown?": 1,
  "others||custom||I am feeling sad": 1
}